lexartifacts/.DS_Store
lexartifacts/__init__.py
lexartifacts/lexical_artifacts.py
lexartifacts/utils.py
lexartifacts-0.1.0.dist-info/METADATA
lexartifacts-0.1.0.dist-info/WHEEL
lexartifacts-0.1.0.dist-info/entry_points.txt
lexartifacts-0.1.0.dist-info/license_files/LICENSE
lexartifacts-0.1.0.dist-info/RECORD
