Metadata-Version: 2.1
Name: lexartifacts
Version: 0.1.0
Summary: A python package for computation and reporting of lexical artifacts
Project-URL: Homepage, https://github.com/dhfbk/hate-speech-artifacts
Author-email: Alan Ramponi <email@example.com>
License: Copyright (c) 2018 The Python Packaging Authority
Classifier: License :: OSI Approved :: MIT License
Classifier: Operating System :: OS Independent
Classifier: Programming Language :: Python :: 3
Requires-Python: >=3.7
Requires-Dist: emoji==1.7.0
Requires-Dist: pandas>=1.2.0
Requires-Dist: transformers>=3.0.0
